Metadata-Version: 1.0
Name: jsys
Version: 1.0
Summary: Opis
Home-page: UNKNOWN
Author: UNKNOWN
Author-email: UNKNOWN
License: UNKNOWN
Platform: UNKNOWN
